SshKeyDeploy/__init__.py
SshKeyDeploy/cli.py
sshkeydeploy-0.0.3.dist-info/METADATA
sshkeydeploy-0.0.3.dist-info/WHEEL
sshkeydeploy-0.0.3.dist-info/entry_points.txt
sshkeydeploy-0.0.3.dist-info/licenses/LICENSE
sshkeydeploy-0.0.3.dist-info/RECORD
