Metadata-Version: 2.3
Name: SshKeyDeploy
Version: 0.0.3
Summary: A CLI tool to create and deploy SSH keys
Project-URL: Homepage, https://github.com/Juliyo/SshKeyDeploy
Author-email: Julio Zamora <julio17795@gmail.com>
License-File: LICENSE
Requires-Dist: paramiko
Requires-Dist: scp
